pyharmony/__init__.py
pyharmony/__main__.py
pyharmony/client.py
pyharmony/discovery.py
pyharmony-1.0.17.dist-info/DESCRIPTION.rst
pyharmony-1.0.17.dist-info/METADATA
pyharmony-1.0.17.dist-info/RECORD
pyharmony-1.0.17.dist-info/WHEEL
pyharmony-1.0.17.dist-info/entry_points.txt
pyharmony-1.0.17.dist-info/metadata.json
pyharmony-1.0.17.dist-info/top_level.txt
