Metadata-Version: 2.0
Name: pyharmony
Version: 1.0.17
Summary: Python library for programmatically using a Logitech Harmony Link or Ultimate Hub.
Home-page: https://github.com/iandday/pyharmony
Author: Ian Day
Author-email: ian236day@gmail.com
License: BSD
Download-URL: https://github.com/iandday/pyharmony/tarball/1.0.17
Keywords: pyharmony
Platform: UNKNOWN
Classifier: Development Status :: 4 - Beta
Classifier: Topic :: Home Automation
Classifier: Intended Audience :: Developers
Classifier: License :: OSI Approved :: BSD License
Classifier: Natural Language :: English
Classifier: Programming Language :: Python :: 3
Classifier: Programming Language :: Python :: 3.3
Classifier: Programming Language :: Python :: 3.5
Requires-Dist: argparse
Requires-Dist: requests
Requires-Dist: sleekxmpp
